src/__init__.py
src/model/__init__.py
src/model/augmentations.py
src/model/cam.py
src/model/dataset.py
src/model/inference.py
src/model/logger.py
src/model/main.py
src/model/micronuclai_predict.py
src/model/models.py
src/model/utils.py
src/utils/__init__.py
src/utils/blur_detect.py
src/utils/czi2ometif.py
src/utils/extract_single_nuclei.py
src/utils/isonuc.py
src/utils/jpeg2ometif.py
micronuclai-0.1.3.dist-info/LICENSE
micronuclai-0.1.3.dist-info/METADATA
micronuclai-0.1.3.dist-info/WHEEL
micronuclai-0.1.3.dist-info/entry_points.txt
micronuclai-0.1.3.dist-info/top_level.txt
micronuclai-0.1.3.dist-info/RECORD
