Metadata-Version: 2.2
Name: micronuclai
Version: 0.1.3
Summary: Automated identification of micronuclei for chromosomal instability (CIN) quantification.
Author-email: "Miguel A. Ibarra-Arellano" <c180l058j@mozmail.com>
License: AGPL-3.0-or-later
Project-URL: Homepage, https://github.com/SchapiroLabor/micronuclAI
Project-URL: Issues, https://github.com/SchapiroLabor/micronuclAI/issues
Keywords: chromosomal instability,cin,micronuclei,micronuclai
Classifier: Programming Language :: Python :: 3.10
Classifier: Programming Language :: Python :: 3.11
Classifier: Programming Language :: Python :: 3.12
Classifier: Operating System :: OS Independent
Classifier: Intended Audience :: Science/Research
Classifier: License :: OSI Approved :: GNU Affero General Public License v3
Requires-Python: >=3.10
License-File: LICENSE
Requires-Dist: torch==2.6.0
Requires-Dist: torchvision
Requires-Dist: numpy==2.2.3
Requires-Dist: pandas==2.2.3
Requires-Dist: scikit_learn==1.6.1
Requires-Dist: mask2bbox==0.0.23
Requires-Dist: lightning==2.5.0
